pymodaq_plugins_flim/VERSION
pymodaq_plugins_flim/__init__.py
pymodaq_plugins_flim/daq_move_plugins/__init__.py
pymodaq_plugins_flim/daq_viewer_plugins/__init__.py
pymodaq_plugins_flim/daq_viewer_plugins/plugins_0D/__init__.py
pymodaq_plugins_flim/daq_viewer_plugins/plugins_1D/__init__.py
pymodaq_plugins_flim/daq_viewer_plugins/plugins_2D/__init__.py
pymodaq_plugins_flim/daq_viewer_plugins/plugins_ND/__init__.py
pymodaq_plugins_flim/daq_viewer_plugins/plugins_ND/daq_NDviewer_FLIM_TH260_PiezoConcept.py
pymodaq_plugins_flim/hardware/__init__.py
pymodaq_plugins_flim-0.1.0.dist-info/LICENSE
pymodaq_plugins_flim-0.1.0.dist-info/METADATA
pymodaq_plugins_flim-0.1.0.dist-info/WHEEL
pymodaq_plugins_flim-0.1.0.dist-info/entry_points.txt
pymodaq_plugins_flim-0.1.0.dist-info/top_level.txt
pymodaq_plugins_flim-0.1.0.dist-info/RECORD
