Metadata-Version: 2.1
Name: pymodaq-plugins-flim
Version: 0.1.0
Summary: Set of PyMoDAQ plugins for FLIM Measurements (Fluorescence Lifetime Imaging Microscopy) (using a conjugation of Time-Correlated Single Photon Counting (TSCPC) and xy stages)
Home-page: https://github.com/CEMES-CNRS/pymodaq_plugins_flim
Author: Sébastien Weber
Author-email: sebastien.weber@cemes.fr
License: MIT
Platform: UNKNOWN
Classifier: Programming Language :: Python :: 3
Classifier: Development Status :: 5 - Production/Stable
Classifier: Environment :: Other Environment
Classifier: Intended Audience :: Science/Research
Classifier: Topic :: Scientific/Engineering :: Human Machine Interfaces
Classifier: Topic :: Scientific/Engineering :: Visualization
Classifier: License :: OSI Approved :: MIT License
Classifier: Operating System :: OS Independent
Classifier: Topic :: Software Development :: Libraries :: Python Modules
Classifier: Topic :: Software Development :: User Interfaces
License-File: LICENSE
Requires-Dist: toml
Requires-Dist: serial
Requires-Dist: scikit-image
